tebetebe/Environment.py
tebetebe/OSMDataset.py
tebetebe/OSRM.py
tebetebe/POIDataset.py
tebetebe/RoutingProfile.py
tebetebe/Scenario.py
tebetebe/__init__.py
tebetebe/defaults.py
tebetebe/utils.py
tebetebe/analysis/AccessIsochrone.py
tebetebe/analysis/ParallelScenarios.py
tebetebe/analysis/RouteComparison.py
tebetebe/analysis/__init__.py
tebetebe/profiles/__init__.py
tebetebe/profiles/bicycle.lua
tebetebe/profiles/car.lua
tebetebe/profiles/foot.lua
tebetebe/profiles/lib/access.lua
tebetebe/profiles/lib/destination.lua
tebetebe/profiles/lib/guidance.lua
tebetebe/profiles/lib/maxspeed.lua
tebetebe/profiles/lib/measure.lua
tebetebe/profiles/lib/pprint.lua
tebetebe/profiles/lib/profile_debugger.lua
tebetebe/profiles/lib/relations.lua
tebetebe/profiles/lib/sequence.lua
tebetebe/profiles/lib/set.lua
tebetebe/profiles/lib/tags.lua
tebetebe/profiles/lib/utils.lua
tebetebe/profiles/lib/way_handlers.lua
tebetebe-0.0.1.dist-info/DESCRIPTION.rst
tebetebe-0.0.1.dist-info/METADATA
tebetebe-0.0.1.dist-info/RECORD
tebetebe-0.0.1.dist-info/WHEEL
tebetebe-0.0.1.dist-info/metadata.json
tebetebe-0.0.1.dist-info/top_level.txt
